geometer/__init__.py
geometer/canvas.py
geometer/colors.py
geometer/grids.py
geometer/reference_image.py
geometer/shapes.py
geometer/solarized.py
geometer/backends/__init__.py
geometer/backends/_quartz.py
geometer/backends/coregraphics.py
geometer/backends/pillow.py
geometer/backends/pythonista.py
geometer/backends/pyx.py
geometer/backends/quartz.py
geometer/scripts/__init__.py
geometriq/__init__.py
geometriq/canvas.py
geometriq/colors.py
geometriq/grids.py
geometriq/reference_image.py
geometriq/shapes.py
geometriq/solarized.py
geometriq/backends/__init__.py
geometriq/backends/_quartz.py
geometriq/backends/coregraphics.py
geometriq/backends/pillow.py
geometriq/backends/pythonista.py
geometriq/backends/pyx.py
geometriq/backends/quartz.py
geometriq/scripts/__init__.py
geometriq-0.0.1.dist-info/LICENSE
geometriq-0.0.1.dist-info/METADATA
geometriq-0.0.1.dist-info/WHEEL
geometriq-0.0.1.dist-info/entry_points.txt
geometriq-0.0.1.dist-info/top_level.txt
geometriq-0.0.1.dist-info/RECORD
