Metadata-Version: 2.1
Name: geometriq
Version: 0.0.1
Summary: A simple API for 2D graphics
Home-page: https://github.com/zacbir/geometriq
Author: Zachery Bir
Author-email: zbir@zacbir.net
License: UNKNOWN
Platform: UNKNOWN
Classifier: Programming Language :: Python :: 3
Classifier: License :: OSI Approved :: MIT License
Classifier: Operating System :: OS Independent
Requires-Dist: click (>=6.0)
Requires-Dist: pyobjc ; platform_system == "Darwin"
